click2cwl/__init__.py
click2cwl/clt.py
click2cwl/cltexport.py
click2cwl/cwl_constructor.py
click2cwl/cwlexport.py
click2cwl/cwlparam.py
click2cwl/entry.py
click2cwl/metadata.py
click2cwl/paramexport.py
click2cwl/tests.py
click2cwl/wf.py
click2cwl-0.4.0.dist-info/METADATA
click2cwl-0.4.0.dist-info/WHEEL
click2cwl-0.4.0.dist-info/RECORD
