Metadata-Version: 2.4
Name: click2cwl
Version: 0.4.0
Summary: Generates CWL documents and associated parameters from a Click CLI definition
Project-URL: Documentation, https://github.com/Terradue/click2cwl#readme
Project-URL: Issues, https://github.com/Terradue/click2cwl/issues
Project-URL: Source, https://github.com/Terradue/click2cwl
Author: Blasco Brauzzi, Farid Yusifli, Francis Charette-Migneault
Author-email: Fabrice Brito <fabrice.brito@terradue.com>, Michele Longobardo <michele.longobardo@terradue.com>, Simone Vaccari <simone.vaccari@terradue.com>
License-Expression: MIT
Keywords: CWL,cli,click
Classifier: Development Status :: 4 - Beta
Classifier: Programming Language :: Python
Classifier: Programming Language :: Python :: 3.7
Classifier: Programming Language :: Python :: 3.8
Classifier: Programming Language :: Python :: 3.9
Classifier: Programming Language :: Python :: 3.10
Classifier: Programming Language :: Python :: 3.11
Classifier: Programming Language :: Python :: 3.12
Classifier: Programming Language :: Python :: Implementation :: CPython
Classifier: Programming Language :: Python :: Implementation :: PyPy
Requires-Python: >=3.7
Requires-Dist: click<9
Requires-Dist: pyyaml
Provides-Extra: test
Requires-Dist: pytest; extra == 'test'
